Metadata-Version: 2.1
Name: bonnette
Version: 0.1.1
Summary: ASGI adapter for Azure Functions
Home-page: https://github.com/erm/bonnette
Author: Jordan Eremieff
Author-email: jordan@eremieff.com
License: MIT
Platform: UNKNOWN
Classifier: License :: OSI Approved :: MIT License
Classifier: Operating System :: OS Independent
Classifier: Programming Language :: Python :: 3
Classifier: Programming Language :: Python :: 3.6
